Workbook
Name Aseguradoras: #REF!
Name Forma_Pago: #REF!
Name RamoIBIS: #REF!
Name SegmentaciónDeDatos_EmpresaFilial: #N/A
Name SegmentaciónDeDatos_FormaDePago: #N/A
Name SegmentaciónDeDatos_Grupo: #N/A
Name SegmentaciónDeDatos_RamoAutoCamiónMotoEtc: #N/A
Name SegmentaciónDeDatos_SubRamo: #N/A
Name SegmentaciónDeDatos_Tipo_de_Flotilla__Empresa___Empleado: #N/A
Name SubRamo: #REF!

Sheet Comentarios Comparativo
B4: Comentarios del Comparativo
B6: Comentarios

Sheet Resumen de Primas
B2: RESUMEN DE PRIMAS
B4: CLIENTE: | C4: =#REF! -> #REF!
C6: Atlas | H6: HDI | K6: Zurich | N6: Quálitas | Q6: Mapfre
C8: ACTUAL | E8: OPCIÓN 1 | F8: OPCIÓN 2 | H8: OPCIÓN 1 | I8: OPCIÓN 2 | K8: OPCIÓN 1 | L8: OPCIÓN 2 | N8: OPCIÓN 1 | O8: OPCIÓN 2 | Q8: OPCIÓN 1 | R8: OPCIÓN 2
B10: UNIDADES | C10: 1 | E10: 1
B11: DERECHOS POR UNIDAD
B13: PRIMA NETA | C13: 1 | E13: 1
B14: DERECHOS | C14: =C11*C10 -> 0 | E14: =E11*E10 -> 0 | F14: =F11*F10 -> 0 | H14: =H11*H10 -> 0 | I14: =I11*I10 -> 0 | K14: =K11*K10 -> 0 | L14: =L11*L10 -> 0 | N14: =N11*N10 -> 0 | O14: =O11*O10 -> 0 | Q14: =Q11*Q10 -> 0 | R14: =R11*R10 -> 0
B15: RECARGOS PAGO FRACCIONADO | C15: =C13*C28 -> #VALUE! | E15: =E13*E28 -> #VALUE! | F15: =F13*E28 -> #VALUE! | H15: =H13*H28 -> #VALUE! | I15: =I13*H28 -> #VALUE! | K15: =K13*K28 -> #VALUE! | L15: =L13*K28 -> #VALUE! | N15: =N13*N28 -> #VALUE! | O15: =O13*N28 -> #VALUE! | Q15: =Q13*Q28 -> #VALUE! | R15: =R13*Q28 -> #VALUE!
B16: IVA | C16: =SUM(C13:C15)*0.16 -> #VALUE! | E16: =SUM(E13:E15)*0.16 -> #VALUE! | F16: =SUM(F13:F15)*0.16 -> #VALUE! | H16: =SUM(H13:H15)*0.16 -> #VALUE! | I16: =SUM(I13:I15)*0.16 -> #VALUE! | K16: =SUM(K13:K15)*0.16 -> #VALUE! | L16: =SUM(L13:L15)*0.16 -> #VALUE! | N16: =SUM(N13:N15)*0.16 -> #VALUE! | O16: =SUM(O13:O15)*0.16 -> #VALUE! | Q16: =SUM(Q13:Q15)*0.16 -> #VALUE! | R16: =SUM(R13:R15)*0.16 -> #VALUE!
B17: PRIMA TOTAL | C17: =SUM(C13:C16) -> #VALUE! | E17: =SUM(E13:E16) -> #VALUE! | F17: =SUM(F13:F16) -> #VALUE! | H17: =SUM(H13:H16) -> #VALUE! | I17: =SUM(I13:I16) -> #VALUE! | K17: =SUM(K13:K16) -> #VALUE! | L17: =SUM(L13:L16) -> #VALUE! | N17: =SUM(N13:N16) -> #VALUE! | O17: =SUM(O13:O16) -> #VALUE! | Q17: =SUM(Q13:Q16) -> #VALUE! | R17: =SUM(R13:R16) -> #VALUE!
B19: PRIMA NETA PROMEDIO | C19: =C13/C10 -> 1 | E19: =IFERROR(E13/E10,0) -> 1 | F19: =IFERROR(F13/F10,0) -> 0 | H19: =IFERROR(H13/H10,0) -> 0 | I19: =IFERROR(I13/I10,0) -> 0 | K19: =IFERROR(K13/K10,0) -> 0 | L19: =IFERROR(L13/L10,0) -> 0 | N19: =IFERROR(N13/N10,0) -> 0 | O19: =IFERROR(O13/O10,0) -> 0 | Q19: =IFERROR(Q13/Q10,0) -> 0 | R19: =IFERROR(R13/R10,0) -> 0
B20: PRIMA TOTAL PROMEDIO | C20: =C17/C10 -> #VALUE! | E20: =IFERROR(E17/E10,0) -> 0 | F20: =IFERROR(F17/F10,0) -> 0 | H20: =IFERROR(H17/H10,0) -> 0 | I20: =IFERROR(I17/I10,0) -> 0 | K20: =IFERROR(K17/K10,0) -> 0 | L20: =IFERROR(L17/L10,0) -> 0 | N20: =IFERROR(N17/N10,0) -> 0 | O20: =IFERROR(O17/O10,0) -> 0 | Q20: =IFERROR(Q17/Q10,0) -> 0 | R20: =IFERROR(R17/R10,0) -> 0
B22: Δ% PRIMA NETA | E22: =E19/$C$19-1 -> 0 | F22: =F19/$C$19-1 -> -1 | H22: =H19/$C$19-1 -> -1 | I22: =I19/$C$19-1 -> -1 | K22: =K19/$C$19-1 -> -1 | L22: =L19/$C$19-1 -> -1 | N22: =N19/$C$19-1 -> -1 | O22: =O19/$C$19-1 -> -1 | Q22: =Q19/$C$19-1 -> -1 | R22: =R19/$C$19-1 -> -1
B23: Δ% PRIMA TOTAL | E23: =E20/$C$20-1 -> #VALUE! | F23: =F20/$C$20-1 -> #VALUE! | H23: =H20/$C$20-1 -> #VALUE! | I23: =I20/$C$20-1 -> #VALUE! | K23: =K20/$C$20-1 -> #VALUE! | L23: =L20/$C$20-1 -> #VALUE! | N23: =N20/$C$20-1 -> #VALUE! | O23: =O20/$C$20-1 -> #VALUE! | Q23: =Q20/$C$20-1 -> #VALUE! | R23: =R20/$C$20-1 -> #VALUE!
B25: DESCRIPCIÓN DE OPCIONES
C26: 2 | D26: 1 | E26: 1 | F26: 1 | G26: 1 | H26: 1 | I26: 1 | J26: 1 | K26: 1 | L26: 1 | M26: 1 | N26: 1 | O26: 1 | P26: 1 | Q26: 1 | R26: 1
B27: RECARGOS POR PAGO FRACCIONADO
B28: SEMESTRAL | C28: =IF(AND($B$28<>$B$29,$B$28<>$B$30,$B$28<>$B$31),0%,VLOOKUP($B28,$B$29:$C$31,2,0)) | E28: =IF(AND($B$28<>$B$29,$B$28<>$B$30,$B$28<>$B$31),0%,VLOOKUP($B28,$B$29:$R$31,SUM($C$26:E26),0)) | H28: =IF(AND($B$28<>$B$29,$B$28<>$B$30,$B$28<>$B$31),0%,VLOOKUP($B28,$B$29:$R$31,SUM($C$26:H26),0)) | K28: =IF(AND($B$28<>$B$29,$B$28<>$B$30,$B$28<>$B$31),0%,VLOOKUP($B28,$B$29:$R$31,SUM($C$26:K26),0)) | N28: =IF(AND($B$28<>$B$29,$B$28<>$B$30,$B$28<>$B$31),0%,VLOOKUP($B28,$B$29:$R$31,SUM($C$26:N26),0)) | Q28: =IF(AND($B$28<>$B$29,$B$28<>$B$30,$B$28<>$B$31),0%,VLOOKUP($B28,$B$29:$R$31,SUM($C$26:Q26),0))
B29: SEMESTRAL | C29: =IFERROR(VLOOKUP(C$6,#REF!,#REF!,0),"") | E29: =IFERROR(VLOOKUP(C$6,#REF!,#REF!,0),"") | H29: =IFERROR(VLOOKUP(H$6,#REF!,#REF!,0),"") | K29: =IFERROR(VLOOKUP(K$6,#REF!,#REF!,0),"") | N29: =IFERROR(VLOOKUP(N$6,#REF!,#REF!,0),"") | Q29: =IFERROR(VLOOKUP(Q$6,#REF!,#REF!,0),"")
B30: TRIMESTRAL | C30: =IFERROR(VLOOKUP(C$6,#REF!,#REF!,0),"") | E30: =IFERROR(VLOOKUP(C$6,#REF!,#REF!,0),"") | F30: =IFERROR(VLOOKUP(F$6,#REF!,#REF!,0),"") | H30: =IFERROR(VLOOKUP(H$6,#REF!,#REF!,0),"") | I30: =IFERROR(VLOOKUP(I$6,#REF!,#REF!,0),"") | K30: =IFERROR(VLOOKUP(K$6,#REF!,#REF!,0),"") | L30: =IFERROR(VLOOKUP(L$6,#REF!,#REF!,0),"") | N30: =IFERROR(VLOOKUP(N$6,#REF!,#REF!,0),"") | O30: =IFERROR(VLOOKUP(O$6,#REF!,#REF!,0),"") | Q30: =IFERROR(VLOOKUP(Q$6,#REF!,#REF!,0),"") | R30: =IFERROR(VLOOKUP(R$6,#REF!,#REF!,0),"")
B31: MENSUAL | C31: =IFERROR(VLOOKUP(C$6,#REF!,#REF!,0),"") | E31: =IFERROR(VLOOKUP(C$6,#REF!,#REF!,0),"") | F31: =IFERROR(VLOOKUP(F$6,#REF!,#REF!,0),"") | H31: =IFERROR(VLOOKUP(H$6,#REF!,#REF!,0),"") | I31: =IFERROR(VLOOKUP(I$6,#REF!,#REF!,0),"") | K31: =IFERROR(VLOOKUP(K$6,#REF!,#REF!,0),"") | L31: =IFERROR(VLOOKUP(L$6,#REF!,#REF!,0),"") | N31: =IFERROR(VLOOKUP(N$6,#REF!,#REF!,0),"") | O31: =IFERROR(VLOOKUP(O$6,#REF!,#REF!,0),"") | Q31: =IFERROR(VLOOKUP(Q$6,#REF!,#REF!,0),"") | R31: =IFERROR(VLOOKUP(R$6,#REF!,#REF!,0),"")
B33: Importes en moneda nacional
B34: Las primas presentadas consideran forma de pago CONTADO.
B37: COMISIÓN % | C37: =C38&"% y "&C39&"%" -> 15% y 13% | E37: =E38&"% y "&E39&"%" -> 15% y 13% | F37: =F38&"% y "&F39&"%" -> % y % | H37: =H38&"% y "&H39&"%" -> % y % | I37: =I38&"% y "&I39&"%" -> % y % | K37: =K38&"% y "&K39&"%" -> % y % | L37: =L38&"% y "&L39&"%" -> % y % | N37: =N38&"% y "&N39&"%" -> % y % | O37: =O38&"% y "&O39&"%" -> % y % | Q37: =Q38&"% y "&Q39&"%" -> % y % | R37: =R38&"% y "&R39&"%" -> % y %
B38: COMISIÓN AUTOS % | C38: 15 | E38: 15
B39: COMISIÓN CAMIONES Y OTROS VEH % | C39: 13 | E39: 13
B40: COMISIÓN MOTOS % | C40: 15 | E40: 13
B41: COMISIÓN (Monto) | C41: =SUM(C42:C44) -> #REF! | E41: =SUM(E42:E44) -> #REF! | F41: =SUM(F42:F44) -> #REF! | H41: =SUM(H42:H44) -> #REF! | I41: =SUM(I42:I44) -> #REF! | K41: =SUM(K42:K44) -> #REF! | L41: =SUM(L42:L44) -> #REF! | N41: =SUM(N42:N44) -> #REF! | O41: =SUM(O42:O44) -> #REF! | Q41: =SUM(Q42:Q44) -> #REF! | R41: =SUM(R42:R44) -> #REF!
B42: COMISIÓN AUTOS | C42: =SUMIFS(#REF!,#REF!,"Automovil")*C38% -> #REF! | E42: =SUMIFS(#REF!,#REF!,"Automovil")*E38% -> #REF! | F42: =SUMIFS(#REF!,#REF!,"Automovil")*D38% -> #REF! | H42: =SUMIFS(#REF!,#REF!,"Automovil")*F38% -> #REF! | I42: =SUMIFS(#REF!,#REF!,"Automovil")*G38% -> #REF! | K42: =SUMIFS(#REF!,#REF!,"Automovil")*I38% -> #REF! | L42: =SUMIFS(#REF!,#REF!,"Automovil")*J38% -> #REF! | N42: =SUMIFS(#REF!,#REF!,"Automovil")*K38% -> #REF! | O42: =SUMIFS(#REF!,#REF!,"Automovil")*L38% -> #REF! | Q42: =SUMIFS(#REF!,#REF!,"Automovil")*M38% -> #REF! | R42: =SUMIFS(#REF!,#REF!,"Automovil")*N38% -> #REF!
B43: COMISIÓN CAMIONES Y OTROS VEH | C43: =SUMIFS(#REF!,#REF!,"Camion")*C39% -> #REF! | E43: =SUMIFS(#REF!,#REF!,"Camion")*C38% -> #REF! | F43: =SUMIFS(#REF!,#REF!,"Camion")*D38% -> #REF! | H43: =SUMIFS(#REF!,#REF!,"Camion")*F38% -> #REF! | I43: =SUMIFS(#REF!,#REF!,"Camion")*G38% -> #REF! | K43: =SUMIFS(#REF!,#REF!,"Camion")*I38% -> #REF! | L43: =SUMIFS(#REF!,#REF!,"Camion")*J38% -> #REF! | N43: =SUMIFS(#REF!,#REF!,"Camion")*K38% -> #REF! | O43: =SUMIFS(#REF!,#REF!,"Camion")*L38% -> #REF! | Q43: =SUMIFS(#REF!,#REF!,"Camion")*M38% -> #REF! | R43: =SUMIFS(#REF!,#REF!,"Camion")*N38% -> #REF!
B44: COMISIÓN MOTOS | C44: =SUMIFS(#REF!,#REF!,"Motocicleta")*C40% -> #REF! | E44: =SUMIFS(#REF!,#REF!,"Motocicleta")*C38% -> #REF! | F44: =SUMIFS(#REF!,#REF!,"Motocicleta")*D38% -> #REF! | H44: =SUMIFS(#REF!,#REF!,"Motocicleta")*F38% -> #REF! | I44: =SUMIFS(#REF!,#REF!,"Motocicleta")*G38% -> #REF! | K44: =SUMIFS(#REF!,#REF!,"Motocicleta")*I38% -> #REF! | L44: =SUMIFS(#REF!,#REF!,"Motocicleta")*J38% -> #REF! | N44: =SUMIFS(#REF!,#REF!,"Motocicleta")*K38% -> #REF! | O44: =SUMIFS(#REF!,#REF!,"Motocicleta")*L38% -> #REF! | Q44: =SUMIFS(#REF!,#REF!,"Motocicleta")*M38% -> #REF! | R44: =SUMIFS(#REF!,#REF!,"Motocicleta")*N38% -> #REF!
B45: SMART WHEELS (Monto) | E45: 100000
B46: INPLANT
B47: INGRESO WTW | C47: =C41+C45+C46 -> #REF! | E47: =E41+E45+E46 -> #REF! | F47: =F41+F45+F46 -> #REF! | H47: =H41+H45+H46 -> #REF! | I47: =I41+I45+I46 -> #REF! | K47: =K41+K45+K46 -> #REF! | L47: =L41+L45+L46 -> #REF! | N47: =N41+N45+N46 -> #REF! | O47: =O41+O45+O46 -> #REF! | Q47: =Q41+Q45+Q46 -> #REF! | R47: =R41+R45+R46 -> #REF!

Sheet Siniestralidad
B4: Siniestralidad
B6: FECHA CORTE SINI | C6: 44459
B7: INICIO DE VIGENCIA | C7: =C8-365 -> #REF!
B8: VIN DE VIGENCIA | C8: =#REF! -> #REF!
B10: Prima Emitida | C10: =#REF! -> #REF!
B11: Prima Anualizada | C11: =#REF! -> #REF!
B12: Monto Siniestro | C12: 9000
B13: Monto Siniestro Anualizado | C13: =C12/($C$6-$C$7)*365 -> #REF!
B14: Siniestralidad % | C14: =IFERROR(C12/C10,"")
B15: Siniestralidad % Anualizada | C15: =IFERROR(C13/C10,"")
B16: Descuento | C16: =C17/C11-1 -> #REF!
B17: Prima Neta Máxima | C17: =#REF! -> #REF!
B18: Siniestralidad % Propuesta | C18: =IFERROR(C13/C17,"")

Sheet Hoja1
A1: Unidad | B1: ID | C1: Nombre del cliente | D1: NombreEnCasoDeSerEmpleado | E1: ApellidoPaternoEnCasoDeSerEmpleado | F1: ApellidoMaternoEnCasoDeSerEmpleado | G1: FormaDePago | H1: Tipo | I1: Marca | J1: Modelo | K1: Año | L1: Color | M1: Chasis | N1: NoMotor | O1: PLACAS | P1: Beneficiarios Preferentes | Q1: ValorDelAuto | R1: Uso | S1: Puertas | T1: Pasajeros | U1: AdaptaciónDescripción | V1: ValorAdaptación | W1: EquipoEspecialDescripción | X1: ValorEquipoEspecial | Y1: IncisoCia | Z1: Acreedor | AA1: Vigencia Inicial | AB1: Vigencia Final | AC1: MenorNombrado1 | AD1: FechaNacimientoMenor1 | AE1: MenorNombrado2 | AF1: FechaNacimientoMenor2 | AG1: MenorNombrado3 | AH1: FechaNacimientoMenor3 | AI1: MenorNombrado4 | AJ1: FechaNacimientoMenor4 | AK1: MenorNombrado5 | AL1: FechaNacimientoMenor5 | AM1: Aseguradora | AN1: Póliza | AO1: Ejecutivo | AP1: Estatus
A2: 1 | B2: 452538 | C2: DISTRIBUIDORA MARTE S. A. | D2: Angel Antonio Balbás Izquierdo | E2: Angel Antonio Balbás Izquierdo | F2: Angel Antonio Balbás Izquierdo | G2: 5 | H2: 17 | I2: 44 | J2: CX-5 | K2: 2015 | L2: AZUL | M2: JM8KE4W37F0278861 | N2: PY 20478484 | O2: P-872FTR | Q2: 120573 | R2: 5 | U2: No | V2: 0 | W2: No | X2: 0 | AA2: 45657 | AB2: 46022 | AM2: 98685 | AN2: 1-AU-92286 | AO2: Lilian Castillo | AP2: Activo
A3: 2 | B3: 452538 | C3: DISTRIBUIDORA MARTE S. A. | D3: Estela Teofila Pérez Villacinda | E3: Estela Teofila Pérez Villacinda | F3: Estela Teofila Pérez Villacinda | G3: 5 | H3: 1 | I3: 44 | J3: PROTEGE 5 | K3: 2003 | L3: GRIS | M3: JM1BJ245431106053 | N3: FS170862 | O3: P-066JJD | Q3: 19847 | R3: 5 | U3: No | V3: 0 | W3: No | X3: 0 | AA3: 45657 | AB3: 46022 | AM3: 98685 | AN3: 1-AU-92286 | AO3: Lilian Castillo | AP3: Activo
A4: 3 | B4: 452538 | C4: DISTRIBUIDORA MARTE S. A. | D4: Edgar Leonel Godoy Mayorga | E4: Edgar Leonel Godoy Mayorga | F4: Edgar Leonel Godoy Mayorga | G4: 5 | H4: 3 | I4: 58 | J4: MOTOCICLETA - | K4: 2019 | L4: AZUL | M4: MD2A12DY1KCH00475 | N4: DJYCJH41382 | O4: M-502LJF | Q4: 10996 | R4: 5 | U4: No | V4: 0 | W4: No | X4: 0 | AA4: 45657 | AB4: 46022 | AM4: 98685 | AN4: 1-AU-92286 | AO4: Lilian Castillo | AP4: Activo
A5: 4 | B5: 452538 | C5: DISTRIBUIDORA MARTE S. A. | D5: Carlos Oscal Samayoa | E5: Carlos Oscal Samayoa | F5: Carlos Oscal Samayoa | G5: 5 | H5: 17 | I5: 28 | J5: TUCSON | K5: 2013 | L5: GRIS | M5: KMHJU81BADU625850 | N5: G4DCU899186 | O5: P-316FMH | Q5: 66158 | R5: 5 | U5: No | V5: 0 | W5: No | X5: 0 | AA5: 45657 | AB5: 46022 | AM5: 98685 | AN5: 1-AU-92286 | AO5: Lilian Castillo | AP5: Activo
A6: 5 | B6: 452538 | C6: DISTRIBUIDORA MARTE S. A. | D6: Erick Mauricio Contreras Rodas | E6: Erick Mauricio Contreras Rodas | F6: Erick Mauricio Contreras Rodas | G6: 5 | H6: 3 | I6: 58 | J6: MOTOCICLETA - | K6: 2017 | L6: AZUL | M6: MD2A76AZ7HWE48130 | N6: PFZWGE02325 | O6: M-832FCZ | Q6: 7542 | R6: 5 | U6: No | V6: 0 | W6: No | X6: 0 | AA6: 45657 | AB6: 46022 | AM6: 98685 | AN6: 1-AU-92286 | AO6: Lilian Castillo | AP6: Activo
A7: 6 | B7: 452538 | C7: DISTRIBUIDORA MARTE S. A. | D7: Cristoper Antony Tolico Arriaza | E7: Cristoper Antony Tolico Arriaza | F7: Cristoper Antony Tolico Arriaza | G7: 5 | H7: 3 | I7: 1382 | J7: HJ125-8 | K7: 2019 | L7: NEGRO | M7: LC6PJK24K0000348 | N7: 156FM1-5A*D2F37736* | O7: M-590GCY | Q7: 6268 | R7: 5 | U7: No | V7: 0 | W7: No | X7: 0 | AA7: 45657 | AB7: 46022 | AM7: 98685 | AN7: 1-AU-92286 | AO7: Lilian Castillo | AP7: Activo
A8: 7 | B8: 452538 | C8: DISTRIBUIDORA MARTE S. A. | D8: Oscar Enrique Gonzalez Ramirez | E8: Oscar Enrique Gonzalez Ramirez | F8: Oscar Enrique Gonzalez Ramirez | G8: 5 | H8: 1 | I8: 44 | J8: MAZDA 2 | K8: 2014 | L8: GRIS | M8: JM1DE1KY9ED182347 | N8: D08914 ZY | O8: P-345JRW | Q8: 33427 | R8: 5 | U8: No | V8: 0 | W8: No | X8: 0 | AA8: 45657 | AB8: 46022 | AM8: 98685 | AN8: 1-AU-92286 | AO8: Lilian Castillo | AP8: Activo
A9: 8 | B9: 452538 | C9: DISTRIBUIDORA MARTE S. A. | D9: Carlos Oscal Samayoa | E9: Carlos Oscal Samayoa | F9: Carlos Oscal Samayoa | G9: 5 | H9: 1 | I9: 117 | J9: SENTRA | K9: 2015 | L9: GRIS | M9: 3N1AB7AP5FY358425 | N9: *MRA8*709585H | O9: P-096HBJ | Q9: 41783 | R9: 5 | U9: No | V9: 0 | W9: No | X9: 0 | AA9: 45657 | AB9: 46022 | AM9: 98685 | AN9: 1-AU-92286 | AO9: Lilian Castillo | AP9: Activo
A10: 9 | B10: 452538 | C10: DISTRIBUIDORA MARTE S. A. | D10: Joel Eduardo Alvarez López | E10: Joel Eduardo Alvarez López | F10: Joel Eduardo Alvarez López | G10: 5 | H10: 1 | I10: 44 | J10: MAZDA3 I SPORT | K10: 2013 | L10: NEGRO | M10: JM1BL1TF5D1728032 | N10: LF11442196 | O10: P-056GJG | Q10: 38689 | R10: 5 | U10: No | V10: 0 | W10: No | X10: 0 | AA10: 45657 | AB10: 46022 | AM10: 98685 | AN10: 1-AU-92286 | AO10: Lilian Castillo | AP10: Activo
A11: 10 | B11: 452538 | C11: DISTRIBUIDORA MARTE S. A. | D11: Ingrid Fabiola Maldonado Pocon | E11: Ingrid Fabiola Maldonado Pocon | F11: Ingrid Fabiola Maldonado Pocon | G11: 5 | H11: 1 | I11: 139 | J11: ECHO | K11: 2001 | L11: VERDE | M11: JTDBT123310144172 | N11: 1NZ 1659631 | O11: P-731FWR | Q11: 0 | R11: 5 | U11: No | V11: 0 | W11: No | X11: 0 | AA11: 45657 | AB11: 46022 | AM11: 98685 | AN11: 1-AU-92286 | AO11: Lilian Castillo | AP11: Activo
A12: 11 | B12: 452538 | C12: DISTRIBUIDORA MARTE S. A. | D12: Josué Fernando Paredes Valle | E12: Josué Fernando Paredes Valle | F12: Josué Fernando Paredes Valle | G12: 5 | H12: 17 | I12: 139 | J12: 4 RUNNER | K12: 2012 | L12: BLANCO | M12: JTEZU4JR3C5038051 | N12: 1GR-A4444385 | O12: P-933FGY | Q12: 117325 | R12: 5 | U12: No | V12: 0 | W12: No | X12: 0 | AA12: 45657 | AB12: 46022 | AM12: 98685 | AN12: 1-AU-92286 | AO12: Lilian Castillo | AP12: Activo
A13: 12 | B13: 452538 | C13: DISTRIBUIDORA MARTE S. A. | D13: Carmen Cecilia Castillo Diaz | E13: Carmen Cecilia Castillo Diaz | F13: Carmen Cecilia Castillo Diaz | G13: 5 | H13: 17 | I13: 27 | J13: CR-V | K13: 2007 | L13: NEGRO | M13: JHLRE48597C033316 | N13: K24Z1 1464657 | O13: P-753JHT | Q13: 43168 | R13: 5 | U13: No | V13: 0 | W13: No | X13: 0 | AA13: 45657 | AB13: 46022 | AM13: 98685 | AN13: 1-AU-92286 | AO13: Lilian Castillo | AP13: Activo
... A55: 54 | B55: 452538 | C55: DISTRIBUIDORA MARTE S. A. | D55: Harold Eduard García Sierra | E55: Harold Eduard García Sierra | F55: Harold Eduard García Sierra | G55: 5 | H55: 17 | I55: 27 | J55: HR-V SPORT AWD | K55: 2020 | L55: GRIS OSCURO POLICROMADO | M55: 3CZRU6H11LM728272 | N55: R18Z9 0630109 | O55: P-084HXD | Q55: 100000 | R55: 5 | U55: No | V55: 0 | W55: No | X55: 0 | AA55: 45657 | AB55: 46022 | AM55: 98685 | AN55: 1-AU-92286 | AO55: Lilian Castillo | AP55: Activo
C56: DISTRIBUIDORA MARTE S. A. | H56: 17 | I56: 137 | J56: TIGUAN | K56: 2016 | M56: WVGZZZ5NZGW000334 | O56: P-658FYX | Q56: 130000 | R56: 5 | AA56: 45657 | AB56: 46022 | AM56: 98685 | AN56: 1-AU-92286 | AO56: Lilian Castillo | AP56: Activo
C57: DISTRIBUIDORA MARTE S. A. | H57: 17 | I57: 27 | J57: HR-V SPORT AWD | K57: 2020 | M57: 3CZRU6H11LM728272 | O57: P-084HXD | Q57: 100000 | R57: 5 | AA57: 45657 | AB57: 46022 | AM57: 98685 | AN57: 1-AU-92286 | AO57: Lilian Castillo | AP57: Activo

Sheet TD-Datos
J3: Valores
A4: Subramo | B4: Empresa | C4: ID | D4: Grupo | E4: FormaDePago | F4: Inicio de Vigencia | G4: IVA | H4: Recargo | I4: Comisión | J4: Inciso | K4: PN | L4: Derechos | M4: PT | N4: Comisión
A5: Automovil | B5: JoseManuel Gordillo Montoya | C5: 352124 | D5: general | E5: M | F5: 44161 | G5: 0.16 | H5: 0.022 | I5: 0.15 | J5: 3 | K5: 600 | L5: 30 | M5: =(K5*(1+H5)+L5)*(1+G5) -> 746.112 | N5: =K5*I5 -> 90
A6: Camion | B6: JoseManuel Gordillo Montoya | C6: 352124 | D6: general2 | E6: A | F6: 44161 | G6: 0.16 | H6: 0.022 | I6: 0.15 | J6: 1 | K6: 200 | L6: 10 | M6: =(K6*(1+H6)+L6)*(1+G6) -> 248.704 | N6: =K6*I6 -> 30
D7: nuevoGreo | E7: M | F7: 44161 | G7: 0.16 | H7: 0.05 | I7: 0.15 | J7: 1 | K7: 2400 | L7: 120 | M7: =(K7*(1+H7)+L7)*(1+G7) -> 3062.4 | N7: =K7*I7 -> 360
C8: 352125 | D8: nuevoGreo | E8: S | F8: 44161 | G8: 0.16 | H8: 0.05 | I8: 0.15 | J8: 1 | K8: 2400 | L8: 120 | M8: =(K8*(1+H8)+L8)*(1+G8) -> 3062.4 | N8: =K8*I8 -> 360
A9: Motocicleta | B9: JoseManuel Gordillo Montoya | C9: 352124 | D9: general2 | E9: A | F9: 44161 | G9: 0.16 | H9: 0.022 | I9: 0.15 | J9: 1 | K9: 200 | L9: 10 | M9: =(K9*(1+H9)+L9)*(1+G9) -> 248.704 | N9: =K9*I9 -> 30
A10: Total general | J10: 7 | K10: 5800 | L10: 290 | M10: =SUM(M5:M9) -> 7368.32 | N10: =SUM(N5:N9) -> 870
M11: =(K11*(1+H11)+L11)*(1+G11) -> 0 | N11: =K11*I11 -> 0
M12: =(K12*(1+H12)+L12)*(1+G12) -> 0 | N12: =K12*I12 -> 0
M13: =(K13*(1+H13)+L13)*(1+G13) -> 0 | N13: =K13*I13 -> 0
M14: =(K14*(1+H14)+L14)*(1+G14) -> 0 | N14: =K14*I14 -> 0
M15: =(K15*(1+H15)+L15)*(1+G15) -> 0 | N15: =K15*I15 -> 0
M16: =(K16*(1+H16)+L16)*(1+G16) -> 0 | N16: =K16*I16 -> 0
M17: =(K17*(1+H17)+L17)*(1+G17) -> 0 | N17: =K17*I17 -> 0
M18: =(K18*(1+H18)+L18)*(1+G18) -> 0 | N18: =K18*I18 -> 0
M19: =(K19*(1+H19)+L19)*(1+G19) -> 0 | N19: =K19*I19 -> 0
M20: =(K20*(1+H20)+L20)*(1+G20) -> 0 | N20: =K20*I20 -> 0
M21: =(K21*(1+H21)+L21)*(1+G21) -> 0 | N21: =K21*I21 -> 0
M22: =(K22*(1+H22)+L22)*(1+G22) -> 0 | N22: =K22*I22 -> 0
... M125: =(K125*(1+H125)+L125)*(1+G125) -> 0 | N125: =K125*I125 -> 0
M126: =SUM(M5:M125) -> 14736.64 | N126: =SUM(N5:N125) -> 1740

Sheet Prueba
B2: RESUMEN DE PRIMAS
B4: CLIENTE: | C4: =#REF! -> #REF!
C14: Atlas | H14: HDI | K14: Mapfre | N14: Quálitas | Q14: Zurich
C16: ACTUAL | E16: OPCIÓN 1 | F16: OPCIÓN 2 | H16: OPCIÓN 1 | I16: OPCIÓN 2 | K16: OPCIÓN 1 | L16: OPCIÓN 2 | N16: OPCIÓN 1 | O16: OPCIÓN 2 | Q16: OPCIÓN 1 | R16: OPCIÓN 2
B18: UNIDADES | C18: =VLOOKUP("Total general",'TD-Prueba'!$A$3:$P$17,'TD-Prueba'!B$2,0) -> 14 | E18: =VLOOKUP("Total general",'TD-Prueba'!$A$3:$AX$1048576,'TD-Prueba'!D2,0) -> 5 | F18: =VLOOKUP("Total general",'TD-Prueba'!$A$3:$AX$1048576,'TD-Prueba'!D2,0) -> 5 | H18: =VLOOKUP("Total general",'TD-Prueba'!$A$3:$AX$1048576,'TD-Prueba'!G$2,0) -> 1 | I18: =VLOOKUP("Total general",'TD-Prueba'!$A$3:$AX$1048576,'TD-Prueba'!G$2,0) -> 1 | K18: =VLOOKUP("Total general",'TD-Prueba'!$A$3:$AX$1048576,'TD-Prueba'!J$2,0) -> 1 | L18: =VLOOKUP("Total general",'TD-Prueba'!$A$3:$AX$1048576,'TD-Prueba'!J$2,0) -> 1 | N18: =VLOOKUP("Total general",'TD-Prueba'!$A$3:$AX$1048576,'TD-Prueba'!M$2,0) -> 1 | O18: =VLOOKUP("Total general",'TD-Prueba'!$A$3:$AX$1048576,'TD-Prueba'!M$2,0) -> 1 | Q18: =VLOOKUP("Total general",'TD-Prueba'!$A$3:$P$17,'TD-Prueba'!P$2,0) -> 1 | R18: =VLOOKUP("Total general",'TD-Prueba'!$A$3:$AX$1048576,'TD-Prueba'!P$2,0) -> 1
B19: DERECHOS POR UNIDAD
B21: PRIMA NETA | C21: =VLOOKUP("Total general",'TD-Prueba'!$A$3:$P$17,'TD-Prueba'!C$2,0) -> 11600 | E21: =VLOOKUP("Total general",'TD-Prueba'!$A$3:$AX$1048576,'TD-Prueba'!E2,0) -> 5 | F21: =VLOOKUP("Total general",'TD-Prueba'!$A$3:$AX$1048576,'TD-Prueba'!F2,0) -> 2 | H21: =VLOOKUP("Total general",'TD-Prueba'!$A$3:$AX$1048576,'TD-Prueba'!H2,0) -> 3 | I21: =VLOOKUP("Total general",'TD-Prueba'!$A$3:$AX$1048576,'TD-Prueba'!I2,0) -> 4 | K21: =VLOOKUP("Total general",'TD-Prueba'!$A$3:$AX$1048576,'TD-Prueba'!K2,0) -> 5 | L21: =VLOOKUP("Total general",'TD-Prueba'!$A$3:$AX$1048576,'TD-Prueba'!L2,0) -> 6 | N21: =VLOOKUP("Total general",'TD-Prueba'!$A$3:$AX$1048576,'TD-Prueba'!N2,0) -> 7 | O21: =VLOOKUP("Total general",'TD-Prueba'!$A$3:$AX$1048576,'TD-Prueba'!O2,0) -> 8 | Q21: =VLOOKUP("Total general",'TD-Prueba'!$A$3:$AX$1048576,'TD-Prueba'!Q2,0) -> 9 | R21: =VLOOKUP("Total general",'TD-Prueba'!$A$3:$AX$1048576,'TD-Prueba'!R2,0) -> 10
B22: DERECHOS | C22: =C19*C18 -> 0 | E22: =E19*E18 -> 0 | F22: =F19*F18 -> 0 | H22: =H19*H18 -> 0 | I22: =I19*I18 -> 0 | K22: =K19*K18 -> 0 | L22: =L19*L18 -> 0 | N22: =N19*N18 -> 0 | O22: =O19*O18 -> 0 | Q22: =Q19*Q18 -> 0 | R22: =R19*R18 -> 0
B23: RECARGOS PAGO FRACCIONADO | C23: =C21*C36 -> #VALUE! | E23: =E21*E36 -> #VALUE! | F23: =F21*E36 -> #VALUE! | H23: =H21*H36 -> #VALUE! | I23: =I21*H36 -> #VALUE! | K23: =K21*K36 -> #VALUE! | L23: =L21*K36 -> #VALUE! | N23: =N21*N36 -> #VALUE! | O23: =O21*N36 -> #VALUE! | Q23: =Q21*Q36 -> #VALUE! | R23: =R21*Q36 -> #VALUE!
B24: IVA | C24: =SUM(C21:C23)*0.16 -> #VALUE! | E24: =SUM(E21:E23)*0.16 -> #VALUE! | F24: =SUM(F21:F23)*0.16 -> #VALUE! | H24: =SUM(H21:H23)*0.16 -> #VALUE! | I24: =SUM(I21:I23)*0.16 -> #VALUE! | K24: =SUM(K21:K23)*0.16 -> #VALUE! | L24: =SUM(L21:L23)*0.16 -> #VALUE! | N24: =SUM(N21:N23)*0.16 -> #VALUE! | O24: =SUM(O21:O23)*0.16 -> #VALUE! | Q24: =SUM(Q21:Q23)*0.16 -> #VALUE! | R24: =SUM(R21:R23)*0.16 -> #VALUE!
B25: PRIMA TOTAL | C25: =SUM(C21:C24) -> #VALUE! | E25: =SUM(E21:E24) -> #VALUE! | F25: =SUM(F21:F24) -> #VALUE! | H25: =SUM(H21:H24) -> #VALUE! | I25: =SUM(I21:I24) -> #VALUE! | K25: =SUM(K21:K24) -> #VALUE! | L25: =SUM(L21:L24) -> #VALUE! | N25: =SUM(N21:N24) -> #VALUE! | O25: =SUM(O21:O24) -> #VALUE! | Q25: =SUM(Q21:Q24) -> #VALUE! | R25: =SUM(R21:R24) -> #VALUE!
B27: PRIMA NETA PROMEDIO | C27: =C21/C18 -> 828.57143 | E27: =IFERROR(E21/E18,0) -> 1 | F27: =IFERROR(F21/F18,0) -> 0.4 | H27: =IFERROR(H21/H18,0) -> 3 | I27: =IFERROR(I21/I18,0) -> 4 | K27: =IFERROR(K21/K18,0) -> 5 | L27: =IFERROR(L21/L18,0) -> 6 | N27: =IFERROR(N21/N18,0) -> 7 | O27: =IFERROR(O21/O18,0) -> 8 | Q27: =IFERROR(Q21/Q18,0) -> 9 | R27: =IFERROR(R21/R18,0) -> 10
B28: PRIMA TOTAL PROMEDIO | C28: =C25/C18 -> #VALUE! | E28: =IFERROR(E25/E18,0) -> 0 | F28: =IFERROR(F25/F18,0) -> 0 | H28: =IFERROR(H25/H18,0) -> 0 | I28: =IFERROR(I25/I18,0) -> 0 | K28: =IFERROR(K25/K18,0) -> 0 | L28: =IFERROR(L25/L18,0) -> 0 | N28: =IFERROR(N25/N18,0) -> 0 | O28: =IFERROR(O25/O18,0) -> 0 | Q28: =IFERROR(Q25/Q18,0) -> 0 | R28: =IFERROR(R25/R18,0) -> 0
B30: Δ% PRIMA NETA | E30: =E27/$C$27-1 -> -0.9987931 | F30: =F27/$C$27-1 -> -0.99951724 | H30: =H27/$C$27-1 -> -0.99637931 | I30: =I27/$C$27-1 -> -0.99517241 | K30: =K27/$C$27-1 -> -0.99396552 | L30: =L27/$C$27-1 -> -0.99275862 | N30: =N27/$C$27-1 -> -0.99155172 | O30: =O27/$C$27-1 -> -0.99034483 | Q30: =Q27/$C$27-1 -> -0.98913793 | R30: =R27/$C$27-1 -> -0.98793103
B31: Δ% PRIMA TOTAL | E31: =E28/$C$28-1 -> #VALUE! | F31: =F28/$C$28-1 -> #VALUE! | H31: =H28/$C$28-1 -> #VALUE! | I31: =I28/$C$28-1 -> #VALUE! | K31: =K28/$C$28-1 -> #VALUE! | L31: =L28/$C$28-1 -> #VALUE! | N31: =N28/$C$28-1 -> #VALUE! | O31: =O28/$C$28-1 -> #VALUE! | Q31: =Q28/$C$28-1 -> #VALUE! | R31: =R28/$C$28-1 -> #VALUE!
B33: DESCRIPCIÓN DE OPCIONES
C34: 2 | D34: 1 | E34: 1 | F34: 1 | G34: 1 | H34: 1 | I34: 1 | J34: 1 | K34: 1 | L34: 1 | M34: 1 | N34: 1 | O34: 1 | P34: 1 | Q34: 1 | R34: 1
B35: RECARGOS POR PAGO FRACCIONADO | E35: 1 | F35: 1 | H35: =E35+1 -> 2 | I35: =F35+1 -> 2 | K35: =H35+1 -> 3 | L35: =I35+1 -> 3 | N35: =K35+1 -> 4 | O35: =L35+1 -> 4 | Q35: =N35+1 -> 5 | R35: =O35+1 -> 5
B36: SEMESTRAL | C36: =IF(AND($B$36<>$B$37,$B$36<>$B$38,$B$36<>$B$39),0%,VLOOKUP($B36,$B$37:$C$39,2,0)) | E36: =IF(AND($B$36<>$B$37,$B$36<>$B$38,$B$36<>$B$39),0%,VLOOKUP($B36,$B$37:$R$39,SUM($C$34:E34),0)) | H36: =IF(AND($B$36<>$B$37,$B$36<>$B$38,$B$36<>$B$39),0%,VLOOKUP($B36,$B$37:$R$39,SUM($C$34:H34),0)) | K36: =IF(AND($B$36<>$B$37,$B$36<>$B$38,$B$36<>$B$39),0%,VLOOKUP($B36,$B$37:$R$39,SUM($C$34:K34),0)) | N36: =IF(AND($B$36<>$B$37,$B$36<>$B$38,$B$36<>$B$39),0%,VLOOKUP($B36,$B$37:$R$39,SUM($C$34:N34),0)) | Q36: =IF(AND($B$36<>$B$37,$B$36<>$B$38,$B$36<>$B$39),0%,VLOOKUP($B36,$B$37:$R$39,SUM($C$34:Q34),0))
B37: SEMESTRAL | C37: =IFERROR(VLOOKUP(C$14,#REF!,#REF!,0),"") | E37: =IFERROR(VLOOKUP(C$14,#REF!,#REF!,0),"") | H37: =IFERROR(VLOOKUP(H$14,#REF!,#REF!,0),"") | K37: =IFERROR(VLOOKUP(K$14,#REF!,#REF!,0),"") | N37: =IFERROR(VLOOKUP(N$14,#REF!,#REF!,0),"") | Q37: =IFERROR(VLOOKUP(Q$14,#REF!,#REF!,0),"")
B38: TRIMESTRAL | C38: =IFERROR(VLOOKUP(C$14,#REF!,#REF!,0),"") | E38: =IFERROR(VLOOKUP(C$14,#REF!,#REF!,0),"") | H38: =IFERROR(VLOOKUP(H$14,#REF!,#REF!,0),"") | K38: =IFERROR(VLOOKUP(K$14,#REF!,#REF!,0),"") | L38: =IFERROR(VLOOKUP(L$14,#REF!,#REF!,0),"") | N38: =IFERROR(VLOOKUP(N$14,#REF!,#REF!,0),"") | O38: =IFERROR(VLOOKUP(O$14,#REF!,#REF!,0),"") | Q38: =IFERROR(VLOOKUP(Q$14,#REF!,#REF!,0),"") | R38: =IFERROR(VLOOKUP(R$14,#REF!,#REF!,0),"")
B39: MENSUAL | C39: =IFERROR(VLOOKUP(C$14,#REF!,#REF!,0),"") | E39: =IFERROR(VLOOKUP(C$14,#REF!,#REF!,0),"") | H39: =IFERROR(VLOOKUP(H$14,#REF!,#REF!,0),"") | I39: =IFERROR(VLOOKUP(I$14,#REF!,#REF!,0),"") | K39: =IFERROR(VLOOKUP(K$14,#REF!,#REF!,0),"") | L39: =IFERROR(VLOOKUP(L$14,#REF!,#REF!,0),"") | N39: =IFERROR(VLOOKUP(N$14,#REF!,#REF!,0),"") | O39: =IFERROR(VLOOKUP(O$14,#REF!,#REF!,0),"") | Q39: =IFERROR(VLOOKUP(Q$14,#REF!,#REF!,0),"") | R39: =IFERROR(VLOOKUP(R$14,#REF!,#REF!,0),"")
B41: Importes en moneda nacional
B42: Las primas presentadas consideran forma de pago CONTADO.
B45: COMISIÓN % | C45: =C46&"% y "&C47&"%" -> 15% y 13% | E45: =E46&"% y "&E47&"%" -> % y % | F45: =F46&"% y "&F47&"%" -> % y % | H45: =H46&"% y "&H47&"%" -> % y % | I45: =I46&"% y "&I47&"%" -> % y % | K45: =K46&"% y "&K47&"%" -> % y % | L45: =L46&"% y "&L47&"%" -> % y % | N45: =N46&"% y "&N47&"%" -> % y % | O45: =O46&"% y "&O47&"%" -> % y % | Q45: =Q46&"% y "&Q47&"%" -> % y % | R45: =R46&"% y "&R47&"%" -> % y %
B46: COMISIÓN AUTOS % | C46: 15
B47: COMISIÓN CAMIONES Y OTROS VEH % | C47: 13
B48: COMISIÓN MOTOS % | C48: 15
B49: COMISIÓN (Monto) | C49: =SUM(C50:C52) -> #REF! | E49: =SUM(E50:E52) -> #REF! | F49: =SUM(F50:F52) -> #REF! | H49: =SUM(H50:H52) -> #REF! | I49: =SUM(I50:I52) -> #REF! | K49: =SUM(K50:K52) -> #REF! | L49: =SUM(L50:L52) -> #REF! | N49: =SUM(N50:N52) -> #REF! | O49: =SUM(O50:O52) -> #REF! | Q49: =SUM(Q50:Q52) -> #REF! | R49: =SUM(R50:R52) -> #REF!
B50: COMISIÓN AUTOS | C50: =SUMIFS(#REF!,#REF!,"Automovil")*C46% -> #REF! | E50: =SUMIFS(#REF!,#REF!,"Automovil")*C46% -> #REF! | F50: =SUMIFS(#REF!,#REF!,"Automovil")*D46% -> #REF! | H50: =SUMIFS(#REF!,#REF!,"Automovil")*F46% -> #REF! | I50: =SUMIFS(#REF!,#REF!,"Automovil")*G46% -> #REF! | K50: =SUMIFS(#REF!,#REF!,"Automovil")*I46% -> #REF! | L50: =SUMIFS(#REF!,#REF!,"Automovil")*J46% -> #REF! | N50: =SUMIFS(#REF!,#REF!,"Automovil")*K46% -> #REF! | O50: =SUMIFS(#REF!,#REF!,"Automovil")*L46% -> #REF! | Q50: =SUMIFS(#REF!,#REF!,"Automovil")*M46% -> #REF! | R50: =SUMIFS(#REF!,#REF!,"Automovil")*N46% -> #REF!
B51: COMISIÓN CAMIONES Y OTROS VEH | C51: =SUMIFS(#REF!,#REF!,"Camion")*C47% -> #REF! | E51: =SUMIFS(#REF!,#REF!,"Camion")*C46% -> #REF! | F51: =SUMIFS(#REF!,#REF!,"Camion")*D46% -> #REF! | H51: =SUMIFS(#REF!,#REF!,"Camion")*F46% -> #REF! | I51: =SUMIFS(#REF!,#REF!,"Camion")*G46% -> #REF! | K51: =SUMIFS(#REF!,#REF!,"Camion")*I46% -> #REF! | L51: =SUMIFS(#REF!,#REF!,"Camion")*J46% -> #REF! | N51: =SUMIFS(#REF!,#REF!,"Camion")*K46% -> #REF! | O51: =SUMIFS(#REF!,#REF!,"Camion")*L46% -> #REF! | Q51: =SUMIFS(#REF!,#REF!,"Camion")*M46% -> #REF! | R51: =SUMIFS(#REF!,#REF!,"Camion")*N46% -> #REF!
B52: COMISIÓN MOTOS | C52: =SUMIFS(#REF!,#REF!,"Motocicleta")*C48% -> #REF! | E52: =SUMIFS(#REF!,#REF!,"Motocicleta")*C46% -> #REF! | F52: =SUMIFS(#REF!,#REF!,"Motocicleta")*D46% -> #REF! | H52: =SUMIFS(#REF!,#REF!,"Motocicleta")*F46% -> #REF! | I52: =SUMIFS(#REF!,#REF!,"Motocicleta")*G46% -> #REF! | K52: =SUMIFS(#REF!,#REF!,"Motocicleta")*I46% -> #REF! | L52: =SUMIFS(#REF!,#REF!,"Motocicleta")*J46% -> #REF! | N52: =SUMIFS(#REF!,#REF!,"Motocicleta")*K46% -> #REF! | O52: =SUMIFS(#REF!,#REF!,"Motocicleta")*L46% -> #REF! | Q52: =SUMIFS(#REF!,#REF!,"Motocicleta")*M46% -> #REF! | R52: =SUMIFS(#REF!,#REF!,"Motocicleta")*N46% -> #REF!
B53: SMART WHEELS (Monto)
B54: INPLANT
B55: INGRESO WTW | C55: =C49+C53+C54 -> #REF! | E55: =E49+E53+E54 -> #REF! | F55: =F49+F53+F54 -> #REF! | H55: =H49+H53+H54 -> #REF! | I55: =I49+I53+I54 -> #REF! | K55: =K49+K53+K54 -> #REF! | L55: =L49+L53+L54 -> #REF! | N55: =N49+N53+N54 -> #REF! | O55: =O49+O53+O54 -> #REF! | Q55: =Q49+Q53+Q54 -> #REF! | R55: =R49+R53+R54 -> #REF!

Sheet TD-Prueba
A2: 1 | B2: 2 | C2: 3 | D2: 4 | E2: 5 | F2: 6 | G2: 7 | H2: 8 | I2: 9 | J2: 10 | K2: 11 | L2: 12 | M2: 13 | N2: 14 | O2: 15 | P2: 16 | Q2: 17 | R2: 18 | S2: 19 | T2: 20 | U2: 21 | V2: 22 | W2: 23 | X2: 24 | Y2: 25 | Z2: 26 | AA2: 27 | AB2: 28 | AC2: 29 | AD2: 30 | AE2: 31 | AF2: 32 | AG2: 33 | AH2: 34 | AI2: 35 | AJ2: 36 | AK2: 37 | AL2: 38 | AM2: 39 | AN2: 40 | AO2: 41 | AP2: 42 | AQ2: 43 | AR2: 44 | AS2: 45 | AT2: 46 | AU2: 47 | AV2: 48 | AW2: 49 | AX2: 50
A3: Etiquetas de fila | B3: Cuenta de Inciso | C3: Suma de PN Anualizada | D3: Suma de Unidades 1 | E3: Suma de Prima Neta 1 | F3: Suma de Op.2 Prima Neta 1 | G3: Suma de Unidades 2 | H3: Suma de Prima Neta 2 | I3: Suma de Op.2 Prima Neta 2 | J3: Suma de Unidades 3 | K3: Suma de Prima Neta 3 | L3: Suma de Op.2 Prima Neta 3 | M3: Suma de Unidades 4 | N3: Suma de Prima Neta 4 | O3: Suma de Op.2 Prima Neta 4 | P3: Suma de Unidades 5 | Q3: Suma de Prima Neta 5 | R3: Suma de Op.2 Prima Neta 5
A4: Empresa | B4: 4 | C4: 800 | D4: 2 | E4: 2 | F4: 2 | G4: 1 | H4: 3 | I4: 4 | J4: 1 | K4: 5 | L4: 6 | M4: 1 | N4: 7 | O4: 8 | P4: 1 | Q4: 9 | R4: 10
A5: Empleado | B5: 10 | C5: 10800 | D5: 3 | E5: 3 | G5: 0 | J5: 0 | M5: 0 | P5: 0
A6: Total general | B6: 14 | C6: 11600 | D6: 5 | E6: 5 | F6: 2 | G6: 1 | H6: 3 | I6: 4 | J6: 1 | K6: 5 | L6: 6 | M6: 1 | N6: 7 | O6: 8 | P6: 1 | Q6: 9 | R6: 10
